{
  "esm/history.js": {
    "bundled": 28795,
    "minified": 12546,
    "gzipped": 3677,
    "treeshaked": {
      "rollup": {
        "code": 208,
        "import_statements": 132
      },
      "webpack": {
        "code": 1324
      }
    }
  },
  "umd/history.js": {
    "bundled": 33769,
    "minified": 12143,
    "gzipped": 4129
  },
  "umd/history.min.js": {
    "bundled": 31208,
    "minified": 10193,
    "gzipped": 3617
  },
  "esm/@maven-io/history.js": {
    "bundled": 28339,
    "minified": 12421,
    "gzipped": 3619,
    "treeshaked": {
      "rollup": {
        "code": 208,
        "import_statements": 132
      },
      "webpack": {
        "code": 1324
      }
    }
  },
  "umd/@maven-io/history.js": {
    "bundled": 33290,
    "minified": 12011,
    "gzipped": 4058
  },
  "umd/@maven-io/history.min.js": {
    "bundled": 30653,
    "minified": 10061,
    "gzipped": 3550
  }
}
